{"loss/gen_loss": 0.6825019180970756, "loss/disc_loss": 0.01674241581825748, "_timestamp": 1665553610.8431911, "_runtime": 13462.21828007698, "_step": 39329, "images": {"_type": "image-file", "sha256": "af0baa7780105ef3835cb4bee0f2018a93b1f7f66a34869aaf36a97127293eea", "size": 116044, "path": "media/images/images_39328_af0baa7780105ef3835c.png", "format": "png", "width": 528, "height": 522, "caption": "LR - HR - SR - dif"}, "thickness and histograms": {"_type": "image-file", "sha256": "f6c11756790e96c5e01d883d86d9207585ff1fb2f06ac8cc917bfa18b803409b", "size": 55817, "path": "media/images/thickness and histograms_39329_f6c11756790e96c5e01d.png", "format": "png", "width": 800, "height": 1000, "caption": "thick LR - hist LR - thick SR - hist SR"}, "_wandb": {"runtime": 13461}}